aiu/__init__.py
aiu/archive_information.py
aiu/archiveit_collection.py
aiu/pandora_collection.py
aiu/timemap.py
aiu/trove_collection.py
aiu/utils.py
aiu/version.py
aiu-0.2.4.data/scripts/fetch_ait_metadata
aiu-0.2.4.data/scripts/generate_seed_statistics
aiu-0.2.4.data/scripts/seeds2warc
aiu-0.2.4.data/scripts/tm2warc
aiu-0.2.4.dist-info/LICENSE
aiu-0.2.4.dist-info/METADATA
aiu-0.2.4.dist-info/WHEEL
aiu-0.2.4.dist-info/top_level.txt
aiu-0.2.4.dist-info/zip-safe
aiu-0.2.4.dist-info/RECORD
