Metadata-Version: 2.1
Name: aiu
Version: 0.2.4
Summary: Tools for for interacting with Archive-It.
Home-page: https://github.com/oduwsdl/archiveit_utilities
Author: Shawn M. Jones, Himarsha Jayanetti
Author-email: jones.shawn.m@gmail.com
License: MIT
Keywords: webarchives memento
Platform: UNKNOWN
Classifier: Development Status :: 3 - Alpha
Classifier: Intended Audience :: Developers
Classifier: Intended Audience :: Information Technology
Classifier: Intended Audience :: Science/Research
Classifier: Topic :: Internet :: WWW/HTTP
Classifier: Topic :: Scientific/Engineering
Classifier: Topic :: Software Development :: Libraries :: Python Modules
Classifier: Topic :: Utilities
Classifier: License :: OSI Approved :: MIT License
Classifier: Programming Language :: Python :: 3.6
Requires-Dist: requests-futures
Requires-Dist: warcio
Requires-Dist: requests
Requires-Dist: bs4
Requires-Dist: html5lib
Requires-Dist: requests-cache (==0.5.2)
